{
  "banner": "banner.png",
  "title": "COME OUT AND PLAY !",
  "description": [
    {
      "text": "잘큼을 대표하는 잘큼프렌즈 친구들을 소개합니다."
    },
    {
      "text": ""
    },
    {
      "text": "톡톡 튀는 외모만큼 저마다의 장점과 개성이 가득합니다. 어쩌면 남몰래 숨겨둔 속깊은 이야기가 있을지도 몰라요."
    },
    {
      "text": "우리 주변을 잘 둘러보면 잘큼프렌즈를 닮은 친구들이 분명히 있을거에요."
    },
    {
      "text": "여러분을 닮은 우리 프렌즈와 함께 빌런을 물리치고, 프렌즈를 구출하고,"
    },
    {
      "text": "다양한 스토리 속에서 탐험하다보면 언제 어디서나 또 다른 프렌즈를 만날 수도 있답니다."
    }
  ],
  "friends": [
    {
      "image": "kenny.png",
      "name": {
        "en": "Kenny",
        "ko": "케니"
      },
      "color": "#954CE7",
      "title": "잘큼타운 대표 골목대장",
      "description": "뜨거운 불같은 성격을 지닌 케니는 잘큼타운 대표 골목대장입니다. 툭하면 싸우고 얼굴에 상처가 가득하지만, 사실은 불의를 참지 못하는 정의의 사도입니다. 누구라도 나쁜 일을 저지르다 걸리면 엄청 혼날지도 몰라요!"
    },
    {
      "image": "porry.png",
      "name": {
        "en": "Porry",
        "ko": "포리"
      },
      "color": "#FC7B00",
      "title": "인기만점 최강 인싸",
      "description": "재미없는 공부는 하지않는 포리는 오늘도 숙제를 안해서 혼이 납니다. 단, 공부만 아니라면 뭐든 자신있어요! 운동도, 그림도, 노래도 너무너무 잘하는 인기만점 최강 인싸! 타고난 비주얼은 덤!!"
    },
    {
      "image": "rain.png",
      "name": {
        "en": "Rain",
        "ko": "레인"
      },
      "color": "#00C4FF",
      "title": "상냥하지만 눈물이 많아요",
      "description": "으앙- 하고 우는 소리에 옆에 있을 땐 귀마개를 가지고 다녀야 할지도 모릅니다. 하지만 속상한 일이 있다면 언제든지 찾아가도 좋아요! 누구보다 세심하게 이야기를 들어줄거에요."
    },
    {
      "image": "fever.png",
      "name": {
        "en": "Fever",
        "ko": "피버"
      },
      "color": "#E51A1A",
      "title": "초집중 게임 마스터",
      "description": "피버는 오늘도 게임 중! 사실 한달 전만 해도 줄넘기에 푹 빠져\n한달동안 줄이 3개나 끊어졌던건 비밀이랍니다. 하나에 빠지면 끝을 보는 초집중력의 달인이에요!!"
    },
    {
      "image": "forkchi.png",
      "name": {
        "en": "Forkchi",
        "ko": "포크치"
      },
      "color": "#FFBC00",
      "title": "귀여운 요리천재",
      "description": "까다로운 입맛의 소유자로, 집에서도 학교에서도 깨작깨작 골라먹어 부모님은 속이 터지지만! 알고보면 모두가 깜짝 놀라는 요리천재입니다. 친구들의 생일마다 특별한 식사를 대접하는 멋진 취미를 갖고 있어요!"
    },
    {
      "image": "ego.png",
      "name": {
        "en": "EGO",
        "ko": "에고"
      },
      "color": "#00499F",
      "title": "이 구역 발명왕!",
      "description": "항상 반대로 행동하고 말도 잘 안듣지만, 기발한 창의력은 단연 일등입니다. 자유롭고 멋진 발상으로 발명한 핫아이템은 언제나 친구들에게 인기만점이에요!"
    }
  ],
  "slider": "slider.png"
}
